investigraph/__init__.py
investigraph/archive.py
investigraph/cache.py
investigraph/cli.py
investigraph/exceptions.py
investigraph/helpers/__init__.py
investigraph/helpers/addresses.py
investigraph/inspect.py
investigraph/logic/__init__.py
investigraph/logic/export.py
investigraph/logic/extract.py
investigraph/logic/load.py
investigraph/logic/seed.py
investigraph/logic/transform.py
investigraph/model/__init__.py
investigraph/model/config.py
investigraph/model/context.py
investigraph/model/mapping.py
investigraph/model/source.py
investigraph/model/stage.py
investigraph/pipeline.py
investigraph/settings.py
investigraph/types.py
investigraph/util.py
investigraph-0.7.1.dist-info/METADATA
investigraph-0.7.1.dist-info/WHEEL
investigraph-0.7.1.dist-info/entry_points.txt
investigraph-0.7.1.dist-info/licenses/LICENSE
investigraph-0.7.1.dist-info/RECORD
