Metadata-Version: 2.4
Name: investigraph
Version: 0.7.1
Summary: etl pipeline for investigations with follow the money data
License-Expression: MIT
License-File: LICENSE
Author: Simon Wörpel
Author-email: simon.woerpel@pm.me
Requires-Python: >=3.11,<4
Classifier: Intended Audience :: Developers
Classifier: Operating System :: OS Independent
Classifier: Programming Language :: Python
Classifier: Programming Language :: Python :: 3.11
Classifier: Programming Language :: Python :: 3.12
Classifier: Programming Language :: Python :: 3.13
Provides-Extra: level
Provides-Extra: postgres
Provides-Extra: redis
Provides-Extra: sql
Requires-Dist: anystore (>=0.4.3,<0.5.0)
Requires-Dist: dateparser (>=1.2.1,<2.0.0)
Requires-Dist: followthemoney (>=4.5.0,<5.0.0)
Requires-Dist: ftmq (>=4.5.0,<5.0.0)
Requires-Dist: plyvel (>=1.5.1,<2.0.0) ; extra == "level"
Requires-Dist: psycopg2 (>=2.9.10,<3.0.0) ; extra == "postgres"
Requires-Dist: redis (>=4.0.0) ; extra == "redis"
Requires-Dist: runpandarun (>=0.6.1,<0.7.0)
Requires-Dist: sqlalchemy (>=2.0.36,<3.0.0) ; extra == "postgres"
Requires-Dist: sqlalchemy (>=2.0.36,<3.0.0) ; extra == "sql"
Project-URL: Documentation, https://docs.investigraph.dev
Project-URL: Homepage, https://investigraph.dev
Project-URL: Issues, https://github.com/dataresearchcenter/investigraph-etl/issues
Project-URL: Repository, https://github.com/dataresearchcenter/investigraph-etl
